phoenix_ai/RAG_Inference_Runner.py
phoenix_ai/__init__.py
phoenix_ai/config_param.py
phoenix_ai/eval_dataset_prep_ground_truth.py
phoenix_ai/loaders.py
phoenix_ai/rag_eval.py
phoenix_ai/rag_evaluation_data_prep.py
phoenix_ai/rag_inference.py
phoenix_ai/utils.py
phoenix_ai/vector_embedding_pipeline.py
phoenix_ai-0.2.8.0.dist-info/METADATA
phoenix_ai-0.2.8.0.dist-info/WHEEL
phoenix_ai-0.2.8.0.dist-info/RECORD
