Metadata-Version: 2.3
Name: phoenix-ai
Version: 0.2.8.0
Summary: GenAI library for RAG , MCP and Agentic AI
License: MIT
Author: Praveen Govindaraj
Author-email: 38414524+Praveengovianalytics@users.noreply.github.com
Requires-Python: >=3.11,<4.0
Classifier: License :: OSI Approved :: MIT License
Classifier: Programming Language :: Python :: 3
Classifier: Programming Language :: Python :: 3.11
Classifier: Programming Language :: Python :: 3.12
Classifier: Programming Language :: Python :: 3.13
Requires-Dist: databricks (>=0.2,<0.3)
Requires-Dist: databricks-vectorsearch (>=0.56,<0.57)
Requires-Dist: faiss-cpu (>=1.11.0,<2.0.0)
Requires-Dist: langchain-community (>=0.3.24,<0.4.0)
Requires-Dist: mlflow (>=2.22.0,<3.0.0)
Requires-Dist: nltk (>=3.9.1,<4.0.0)
Requires-Dist: numpy (>=2.2.5,<3.0.0)
Requires-Dist: openai (>=1.78.1,<2.0.0)
Requires-Dist: openpyxl (>=3.1.5,<4.0.0)
Requires-Dist: pandas (>=2.2.3,<3.0.0)
Requires-Dist: pymupdf (>=1.25.5,<2.0.0)
Requires-Dist: pypdf (>=5.5.0,<6.0.0)
Requires-Dist: pypdf2 (>=3.0.1,<4.0.0)
Requires-Dist: python-docx (>=1.1.2,<2.0.0)
Requires-Dist: scikit-learn (>=1.6.1,<2.0.0)
Requires-Dist: tiktoken (>=0.9.0,<0.10.0)
Requires-Dist: unstructured (>=0.17.2,<0.18.0)
